Metadata-Version: 2.1
Name: campussquare
Version: 0.0.8
Summary: Campus Square
Home-page: https://github.com/uec-world-dominators/campussquare
Author: shosatojp
Author-email: me@shosato.jp
License: Type license() to see the full license text
Platform: UNKNOWN
Classifier: Programming Language :: Python :: 3
Requires-Python: >=3.6
